strava_mcp/__init__.py
strava_mcp/api.py
strava_mcp/auth.py
strava_mcp/config.py
strava_mcp/main.py
strava_mcp/models.py
strava_mcp/oauth_server.py
strava_mcp/server.py
strava_mcp/service.py
strava_mcp-0.5.0.dist-info/METADATA
strava_mcp-0.5.0.dist-info/WHEEL
strava_mcp-0.5.0.dist-info/entry_points.txt
strava_mcp-0.5.0.dist-info/licenses/LICENSE
strava_mcp-0.5.0.dist-info/RECORD
