Metadata-Version: 2.4
Name: strava-mcp
Version: 0.5.0
Summary: Strava integration for MCP
Author: Yorrick Jansen
License: MIT
License-File: LICENSE
Keywords: api,mcp,strava
Classifier: License :: OSI Approved :: MIT License
Classifier: Operating System :: OS Independent
Classifier: Programming Language :: Python :: 3
Requires-Python: >=3.13
Requires-Dist: fastapi>=0.115.11
Requires-Dist: httpx>=0.28.1
Requires-Dist: mcp[cli]>=1.5.0
Requires-Dist: pydantic-settings>=2.8.1
Requires-Dist: pydantic>=2.10.6
